[
  {
    "id": 1,
    "image": "/assets/img/01.jpg",
    "icon": "icon flaticon-home-1",
    "title": "Архитектур",
    "content": "Архитектур гэдэг нь барилга байгууламжийг төлөвлөх, зохион бүтээх, барих урлаг, шинжлэх ухаан юм. ."
  },
  {
    "id": 2,
    "image": "/assets/img/02.jpg",
    "icon": "icon flaticon-living-room",
    "title": "Дотоод засал чимэглэл",
    "content": "Архитектур гэдэг нь барилга байгууламжийг төлөвлөх, зохион бүтээх, барих урлаг, шинжлэх ухаан юм. ."
  },
  {
    "id": 3,
    "image": "/assets/img/03.jpg",
    "icon": "icon flaticon-interior-design",
    "title": "3D загварчлал",
    "content": "Архитектур гэдэг нь барилга байгууламжийг төлөвлөх, зохион бүтээх, барих урлаг, шинжлэх ухаан юм. ."
  }
]
